tacotree_lab/__init__.py
tacotree_lab-1.0.0.dist-info/LICENSE
tacotree_lab-1.0.0.dist-info/METADATA
tacotree_lab-1.0.0.dist-info/WHEEL
tacotree_lab-1.0.0.dist-info/top_level.txt
tacotree_lab-1.0.0.dist-info/RECORD
